{
    "attributes": {
        "base": {
            "otx_key": true
        },
        "event_int": {
            "otx_key": true
        },
        "face_name": {
            "otx_key": true
        },
        "fisc_tag": {
            "otx_key": true
        },
        "fnigh": {
            "otx_key": false
        },
        "fopen": {
            "otx_key": false
        },
        "owner_name": {
            "otx_key": true
        },
        "pick": {
            "otx_key": false
        },
        "road": {
            "otx_key": true
        }
    },
    "idea_number": "br00023",
    "dimens": [
        "bud_item_factunit"
    ]
}